{
    "products": [
        {
            "id": "QV-LOA-005",
            "name": "Loa E3 BR 8.5/BR115 (Loa Cột)",
            "slug": "loa-e3-br-85-br115-loa-cot",
            "categorySlug": "loa-karaoke",
            "brand": "E3 Audio",
            "priceVND": 27500000,
            "description": "Loa cột E3 BR 8.5/BR115 với thiết kế thon gọn, phù hợp không gian hẹp. Âm thanh trong trẻo, bass ấm.",
            "shortDescription": "Loa cột thiết kế thon gọn cho không gian hẹp",
            "specifications": "{\"Loại\":\"Loa cột\",\"Công suất\":\"300W RMS\"}",
            "warranty": "24 tháng",
            "imageFile": "loa_e3_br_8.5__br115_(loa_cột).png",
            "stockQuantity": 10,
            "featured": false
        },
        {
            "id": "QV-LOA-007",
            "name": "Loa E3 MK 12 (3 Tấc)",
            "slug": "loa-e3-mk-12-3-tac",
            "categorySlug": "loa-karaoke",
            "brand": "E3 Audio",
            "priceVND": 27500000,
            "description": "Loa karaoke E3 MK 12 bass 12 inch (3 tấc), công suất 400W RMS. Phù hợp cho gia đình và kinh doanh nhỏ.",
            "shortDescription": "Loa 12 inch công suất 400W cho gia đình",
            "specifications": "{\"Bass\":\"12 inch\",\"Công suất\":\"400W RMS\",\"Trở kháng\":\"8Ω\"}",
            "warranty": "24 tháng",
            "imageFile": "loa_e3_mk_12_(3_tấc).png",
            "stockQuantity": 15,
            "featured": false
        },
        {
            "id": "QV-LOA-008",
            "name": "Loa Sub E3 Kép RS218",
            "slug": "loa-sub-e3-kep-rs218",
            "categorySlug": "loa-sub",
            "brand": "E3 Audio",
            "priceVND": 27000000,
            "originalPriceVND": 38000000,
            "description": "Loa sub đôi E3 RS218 với 2 bass 18 inch, công suất 1000W RMS. Bass cực sâu cho phòng karaoke lớn.",
            "shortDescription": "Loa sub đôi 18 inch công suất 1000W",
            "specifications": "{\"Bass\":\"2x 18 inch\",\"Công suất\":\"1000W RMS\",\"Tần số\":\"30Hz-200Hz\"}",
            "warranty": "24 tháng",
            "imageFile": "loa_sub_e3_kép_rs218.png",
            "stockQuantity": 5,
            "featured": true
        },
        {
            "id": "QV-LOA-009",
            "name": "Loa CAF SG-12",
            "slug": "loa-caf-sg-12",
            "categorySlug": "loa-karaoke",
            "brand": "CAF",
            "priceVND": 25000000,
            "originalPriceVND": 27000000,
            "description": "Loa karaoke CAF SG-12 với thiết kế sang trọng, bass 12 inch cho âm thanh cân bằng.",
            "shortDescription": "Loa karaoke 12 inch thiết kế sang trọng",
            "specifications": "{\"Bass\":\"12 inch\",\"Công suất\":\"350W RMS\",\"Trở kháng\":\"8Ω\"}",
            "warranty": "24 tháng",
            "imageFile": "loa_caf_sg-12.png",
            "stockQuantity": 12,
            "featured": false
        },
        {
            "id": "QV-LOA-010",
            "name": "Loa E3 DS10II",
            "slug": "loa-e3-ds10ii",
            "categorySlug": "loa-karaoke",
            "brand": "E3 Audio",
            "priceVND": 25000000,
            "description": "Loa karaoke E3 DS10II bass 10 inch, phù hợp phòng nhỏ và vừa. Âm thanh trong trẻo.",
            "shortDescription": "Loa 10 inch cho phòng nhỏ và vừa",
            "specifications": "{\"Bass\":\"10 inch\",\"Công suất\":\"300W RMS\"}",
            "warranty": "24 tháng",
            "imageFile": "loa_e3_ds10ii.png",
            "stockQuantity": 18,
            "featured": false
        },
        {
            "id": "QV-LOA-011",
            "name": "Loa E3 VX12 (3 Tấc)",
            "slug": "loa-e3-vx12-3-tac",
            "categorySlug": "loa-karaoke",
            "brand": "E3 Audio",
            "priceVND": 22000000,
            "description": "Loa karaoke E3 VX12 bass 12 inch với giá tốt, phù hợp cho gia đình.",
            "shortDescription": "Loa 12 inch giá tốt cho gia đình",
            "specifications": "{\"Bass\":\"12 inch\",\"Công suất\":\"350W RMS\"}",
            "warranty": "24 tháng",
            "imageFile": "loa_e3_vx12_(3_tấc).png",
            "stockQuantity": 20,
            "featured": false
        },
        {
            "id": "QV-LOA-012",
            "name": "Loa CAF LAVO-112",
            "slug": "loa-caf-lavo-112",
            "categorySlug": "loa-karaoke",
            "brand": "CAF",
            "priceVND": 20000000,
            "originalPriceVND": 21000000,
            "description": "Loa karaoke CAF LAVO-112 với thiết kế hiện đại, bass 12 inch cho âm thanh sống động.",
            "shortDescription": "Loa 12 inch thiết kế hiện đại",
            "specifications": "{\"Bass\":\"12 inch\",\"Công suất\":\"300W RMS\"}",
            "warranty": "24 tháng",
            "imageFile": "loa_caf_lavo-112.png",
            "stockQuantity": 15,
            "featured": false
        },
        {
            "id": "QV-LOA-013",
            "name": "Loa Sub E3 BR 118",
            "slug": "loa-sub-e3-br-118",
            "categorySlug": "loa-sub",
            "brand": "E3 Audio",
            "priceVND": 18500000,
            "description": "Loa sub E3 BR 118 với bass 18 inch đơn, công suất 600W. Bass sâu cho phòng vừa.",
            "shortDescription": "Loa sub 18 inch đơn công suất 600W",
            "specifications": "{\"Bass\":\"18 inch\",\"Công suất\":\"600W RMS\"}",
            "warranty": "24 tháng",
            "imageFile": "loa_sub_e3_br_118.png",
            "stockQuantity": 10,
            "featured": false
        },
        {
            "id": "QV-LOA-014",
            "name": "Loa E3 R-12 (3 Tấc)",
            "slug": "loa-e3-r-12-3-tac",
            "categorySlug": "loa-karaoke",
            "brand": "E3 Audio",
            "priceVND": 18000000,
            "originalPriceVND": 21000000,
            "description": "Loa karaoke E3 R-12 với giá ưu đãi, phù hợp ngân sách hạn chế.",
            "shortDescription": "Loa 12 inch giá ưu đãi",
            "specifications": "{\"Bass\":\"12 inch\",\"Công suất\":\"300W RMS\"}",
            "warranty": "24 tháng",
            "imageFile": "loa_e3_r-12_(3_tấc).png",
            "stockQuantity": 25,
            "featured": false
        },
        {
            "id": "QV-LOA-015",
            "name": "Loa E3 KC12 (3 Tấc)",
            "slug": "loa-e3-kc12-3-tac",
            "categorySlug": "loa-karaoke",
            "brand": "E3 Audio",
            "priceVND": 17000000,
            "description": "Loa karaoke E3 KC12 nhỏ gọn, tiết kiệm cho gia đình.",
            "shortDescription": "Loa 12 inch nhỏ gọn tiết kiệm",
            "specifications": "{\"Bass\":\"12 inch\",\"Công suất\":\"250W RMS\"}",
            "warranty": "24 tháng",
            "imageFile": "loa_e3_kc12_(3_tấc).png",
            "stockQuantity": 20,
            "featured": false
        },
        {
            "id": "QV-LOA-016",
            "name": "Loa Sub CAF CA-18S",
            "slug": "loa-sub-caf-ca-18s",
            "categorySlug": "loa-sub",
            "brand": "CAF",
            "priceVND": 15000000,
            "originalPriceVND": 16000000,
            "description": "Loa sub CAF CA-18S bass 18 inch đơn, công suất 500W. Giá tốt cho phòng vừa.",
            "shortDescription": "Loa sub 18 inch đơn giá tốt",
            "specifications": "{\"Bass\":\"18 inch\",\"Công suất\":\"500W RMS\"}",
            "warranty": "24 tháng",
            "imageFile": "caf_ca-18s.png",
            "stockQuantity": 12,
            "featured": false
        },
        {
            "id": "QV-LOA-017",
            "name": "Loa CAF MC12",
            "slug": "loa-caf-mc12",
            "categorySlug": "loa-karaoke",
            "brand": "CAF",
            "priceVND": 15000000,
            "originalPriceVND": 16000000,
            "description": "Loa karaoke CAF MC12 phổ thông với chất lượng ổn định.",
            "shortDescription": "Loa 12 inch phổ thông chất lượng",
            "specifications": "{\"Bass\":\"12 inch\",\"Công suất\":\"250W RMS\"}",
            "warranty": "24 tháng",
            "imageFile": "loa_caf_mc12.png",
            "stockQuantity": 18,
            "featured": false
        },
        {
            "id": "QV-LOA-018",
            "name": "Loa Sub E3 BR 115",
            "slug": "loa-sub-e3-br-115",
            "categorySlug": "loa-sub",
            "brand": "E3 Audio",
            "priceVND": 13900000,
            "description": "Loa sub E3 BR 115 bass 15 inch, công suất 400W. Phù hợp phòng nhỏ.",
            "shortDescription": "Loa sub 15 inch cho phòng nhỏ",
            "specifications": "{\"Bass\":\"15 inch\",\"Công suất\":\"400W RMS\"}",
            "warranty": "24 tháng",
            "imageFile": "loa_sub_e3_br_115.png",
            "stockQuantity": 15,
            "featured": false
        },
        {
            "id": "QV-LOA-019",
            "name": "Sub CAF MC-115S",
            "slug": "sub-caf-mc-115s",
            "categorySlug": "loa-sub",
            "brand": "CAF",
            "priceVND": 12000000,
            "originalPriceVND": 13000000,
            "description": "Loa sub CAF MC-115S bass 15 inch, giá rẻ cho gia đình.",
            "shortDescription": "Loa sub 15 inch giá rẻ",
            "specifications": "{\"Bass\":\"15 inch\",\"Công suất\":\"350W RMS\"}",
            "warranty": "24 tháng",
            "imageFile": "sub_caf_mc-115s.png",
            "stockQuantity": 20,
            "featured": false
        },
        {
            "id": "QV-MIX-004",
            "name": "Vang Số CAF A5",
            "slug": "vang-so-caf-a5",
            "categorySlug": "vang-so-mixer",
            "brand": "CAF",
            "priceVND": 5000000,
            "originalPriceVND": 5500000,
            "description": "Vang số CAF A5 phổ thông với các tính năng cơ bản, phù hợp gia đình.",
            "shortDescription": "Vang số phổ thông cho gia đình",
            "specifications": "{\"DSP\":\"24-bit\",\"Chống hú\":\"Có\"}",
            "warranty": "12 tháng",
            "imageFile": "vang_caf_a5.png",
            "stockQuantity": 35,
            "featured": false
        },
        {
            "id": "QV-MIC-004",
            "name": "Micro Không Dây E3 Q-100",
            "slug": "micro-khong-day-e3-q-100",
            "categorySlug": "microphone",
            "brand": "E3 Audio",
            "priceVND": 8500000,
            "description": "Micro không dây E3 Q-100 với công nghệ UHF ổn định, phù hợp gia đình.",
            "shortDescription": "Micro UHF ổn định cho gia đình",
            "specifications": "{\"Công nghệ\":\"UHF\",\"Đáp ứng\":\"50-15000Hz\"}",
            "warranty": "12 tháng",
            "imageFile": "micro_không_dây_e3_q-100.png",
            "stockQuantity": 25,
            "featured": false
        },
        {
            "id": "QV-MIC-005",
            "name": "Micro Không Dây CAF MH-666",
            "slug": "micro-khong-day-caf-mh-666",
            "categorySlug": "microphone",
            "brand": "CAF",
            "priceVND": 6000000,
            "originalPriceVND": 6500000,
            "description": "Micro không dây CAF MH-666 với giá tốt, chất lượng ổn định.",
            "shortDescription": "Micro không dây giá tốt",
            "specifications": "{\"Công nghệ\":\"UHF\"}",
            "warranty": "12 tháng",
            "imageFile": "caf_mh-666.png",
            "stockQuantity": 30,
            "featured": false
        },
        {
            "id": "QV-MIC-006",
            "name": "Micro Không Dây E3 M560",
            "slug": "micro-khong-day-e3-m560",
            "categorySlug": "microphone",
            "brand": "E3 Audio",
            "priceVND": 5000000,
            "originalPriceVND": 6500000,
            "description": "Micro không dây E3 M560 với giá ưu đãi cho gia đình.",
            "shortDescription": "Micro không dây giá ưu đãi",
            "specifications": "{\"Công nghệ\":\"UHF\"}",
            "warranty": "12 tháng",
            "imageFile": "micro_không_dây_e3_-_m560.png",
            "stockQuantity": 35,
            "featured": false
        },
        {
            "id": "QV-MIC-007",
            "name": "Micro Không Dây E3 Q16",
            "slug": "micro-khong-day-e3-q16",
            "categorySlug": "microphone",
            "brand": "E3 Audio",
            "priceVND": 5000000,
            "originalPriceVND": 6500000,
            "description": "Micro không dây E3 Q16 entry-level cho người mới bắt đầu.",
            "shortDescription": "Micro entry-level cho người mới",
            "specifications": "{\"Công nghệ\":\"UHF\"}",
            "warranty": "12 tháng",
            "imageFile": "micro_không_dây_e3_q16.png",
            "stockQuantity": 40,
            "featured": false
        },
        {
            "id": "QV-AMP-002",
            "name": "Cục Đẩy E3 PA-4.10/TX 12000 Pro (4 Kênh)",
            "slug": "cuc-day-e3-pa-410-tx-12000-pro",
            "categorySlug": "amply-cuc-day",
            "brand": "E3 Audio",
            "priceVND": 25000000,
            "originalPriceVND": 29000000,
            "description": "Cục đẩy 4 kênh E3 PA-4.10 với công suất lớn, Class D hiệu suất cao.",
            "shortDescription": "Cục đẩy 4 kênh Class D công suất lớn",
            "specifications": "{\"Số kênh\":\"4\",\"Công suất\":\"4x1000W@4Ω\",\"Class\":\"D\"}",
            "warranty": "24 tháng",
            "imageFile": "đẩy_e3_-_pa_4.10_tx_12000_pro_(_4_kênh).png",
            "stockQuantity": 10,
            "featured": false
        },
        {
            "id": "QV-AMP-003",
            "name": "Cục Đẩy E3 PA-4.8 (4 Kênh)",
            "slug": "cuc-day-e3-pa-48-4-kenh",
            "categorySlug": "amply-cuc-day",
            "brand": "E3 Audio",
            "priceVND": 22000000,
            "originalPriceVND": 26000000,
            "description": "Cục đẩy 4 kênh E3 PA-4.8 công suất 800W mỗi kênh.",
            "shortDescription": "Cục đẩy 4 kênh 800W/kênh",
            "specifications": "{\"Số kênh\":\"4\",\"Công suất\":\"4x800W@4Ω\"}",
            "warranty": "24 tháng",
            "imageFile": "đẩy_e3_-_pa_4.8_(_4_kênh).png",
            "stockQuantity": 12,
            "featured": false
        },
        {
            "id": "QV-AMP-004",
            "name": "Cục Đẩy E3 F4.8 (4 Kênh)",
            "slug": "cuc-day-e3-f48-4-kenh",
            "categorySlug": "amply-cuc-day",
            "brand": "E3 Audio",
            "priceVND": 18000000,
            "originalPriceVND": 19000000,
            "description": "Cục đẩy 4 kênh E3 F4.8 với giá tốt cho hệ thống vừa.",
            "shortDescription": "Cục đẩy 4 kênh giá tốt",
            "specifications": "{\"Số kênh\":\"4\",\"Công suất\":\"4x600W@4Ω\"}",
            "warranty": "24 tháng",
            "imageFile": "đẩy_e3_-_f4.8_(_4_kênh).png",
            "stockQuantity": 15,
            "featured": false
        },
        {
            "id": "QV-AMP-005",
            "name": "Cục Đẩy E3 F3.12 (3 Kênh)",
            "slug": "cuc-day-e3-f312-3-kenh",
            "categorySlug": "amply-cuc-day",
            "brand": "E3 Audio",
            "priceVND": 18000000,
            "description": "Cục đẩy 3 kênh E3 F3.12, phù hợp cấu hình 2 loa + 1 sub.",
            "shortDescription": "Cục đẩy 3 kênh cho 2 loa + 1 sub",
            "specifications": "{\"Số kênh\":\"3\",\"Công suất\":\"3x1200W@4Ω\"}",
            "warranty": "24 tháng",
            "imageFile": "đẩy_e3_-_f3.12_(3_kênh).png",
            "stockQuantity": 10,
            "featured": false
        },
        {
            "id": "QV-AMP-006",
            "name": "Cục Đẩy CAF QUEEN 48X",
            "slug": "cuc-day-caf-queen-48x",
            "categorySlug": "amply-cuc-day",
            "brand": "CAF",
            "priceVND": 17000000,
            "originalPriceVND": 18000000,
            "description": "Cục đẩy CAF QUEEN 48X với thiết kế đẹp mắt và công suất ổn định.",
            "shortDescription": "Cục đẩy CAF thiết kế đẹp",
            "specifications": "{\"Công suất\":\"2x1200W@4Ω\"}",
            "warranty": "24 tháng",
            "imageFile": "caf_queen_48x.png",
            "stockQuantity": 8,
            "featured": false
        },
        {
            "id": "QV-DK-006",
            "name": "Cục Đẩy Công Suất E3 PA-612",
            "slug": "cuc-day-cong-suat-e3-pa-612",
            "categorySlug": "amply-cuc-day",
            "brand": "E3 Audio",
            "priceVND": 17000000,
            "description": "Cục đẩy E3 PA-612 cao cấp với 6 kênh đẩy riêng biệt.",
            "shortDescription": "Cục đẩy 6 kênh cao cấp",
            "specifications": "{\"Số kênh\":\"6\",\"Công suất\":\"6x500W@4Ω\"}",
            "warranty": "24 tháng",
            "imageFile": "cục_đẩy_công_suất_e3_pa-612.png",
            "stockQuantity": 6,
            "featured": false
        },
        {
            "id": "QV-AMP-007",
            "name": "Cục Đẩy E3 PA-2.8 (2 Kênh)",
            "slug": "cuc-day-e3-pa-28-2-kenh",
            "categorySlug": "amply-cuc-day",
            "brand": "E3 Audio",
            "priceVND": 13800000,
            "originalPriceVND": 15000000,
            "description": "Cục đẩy 2 kênh E3 PA-2.8 với công suất 800W mỗi kênh.",
            "shortDescription": "Cục đẩy 2 kênh 800W/kênh",
            "specifications": "{\"Số kênh\":\"2\",\"Công suất\":\"2x800W@4Ω\"}",
            "warranty": "24 tháng",
            "imageFile": "đẩy_e3_-_pa_2.8_(_2_kênh).png",
            "stockQuantity": 15,
            "featured": false
        },
        {
            "id": "QV-AMP-008",
            "name": "Amply CAF LOTUS 668",
            "slug": "amply-caf-lotus-668",
            "categorySlug": "amply-cuc-day",
            "brand": "CAF",
            "priceVND": 11500000,
            "originalPriceVND": 12500000,
            "description": "Amply CAF LOTUS 668 tích hợp cho gia đình, dễ sử dụng.",
            "shortDescription": "Amply tích hợp cho gia đình",
            "specifications": "{\"Công suất\":\"2x300W\"}",
            "warranty": "24 tháng",
            "imageFile": "caf_lotus_668.png",
            "stockQuantity": 20,
            "featured": false
        },
        {
            "id": "QV-AMP-009",
            "name": "Cục Đẩy E3 PA-2.5 (2 Kênh)",
            "slug": "cuc-day-e3-pa-25-2-kenh",
            "categorySlug": "amply-cuc-day",
            "brand": "E3 Audio",
            "priceVND": 10900000,
            "originalPriceVND": 12000000,
            "description": "Cục đẩy 2 kênh E3 PA-2.5 với công suất 500W mỗi kênh.",
            "shortDescription": "Cục đẩy 2 kênh 500W/kênh",
            "specifications": "{\"Số kênh\":\"2\",\"Công suất\":\"2x500W@4Ω\"}",
            "warranty": "24 tháng",
            "imageFile": "đẩy_e3_-_pa_2.5_(_2_kênh).png",
            "stockQuantity": 18,
            "featured": false
        },
        {
            "id": "QV-AMP-010",
            "name": "Cục Đẩy CAF TS-28",
            "slug": "cuc-day-caf-ts-28",
            "categorySlug": "amply-cuc-day",
            "brand": "CAF",
            "priceVND": 9000000,
            "originalPriceVND": 9500000,
            "description": "Cục đẩy CAF TS-28 entry-level với giá rẻ.",
            "shortDescription": "Cục đẩy entry-level giá rẻ",
            "specifications": "{\"Công suất\":\"2x400W@4Ω\"}",
            "warranty": "24 tháng",
            "imageFile": "caf_ts-28.png",
            "stockQuantity": 25,
            "featured": false
        },
        {
            "id": "QV-AMP-011",
            "name": "Vang Liền Công Suất D-2.5",
            "slug": "vang-lien-cong-suat-d-25",
            "categorySlug": "amply-cuc-day",
            "brand": "E3 Audio",
            "priceVND": 8200000,
            "originalPriceVND": 9500000,
            "description": "Vang số liền công suất D-2.5, giải pháp all-in-one cho gia đình.",
            "shortDescription": "Vang liền đẩy all-in-one",
            "specifications": "{\"Vang\":\"DSP 24-bit\",\"Công suất\":\"2x250W\"}",
            "warranty": "24 tháng",
            "imageFile": "vang_liền_công_suất_d_-_2.5.png",
            "stockQuantity": 22,
            "featured": false
        },
        {
            "id": "QV-DAU-002",
            "name": "Đầu Karaoke CAF QS-108",
            "slug": "dau-karaoke-caf-qs-108",
            "categorySlug": "dau-karaoke",
            "brand": "CAF",
            "priceVND": 3000000,
            "originalPriceVND": 4100000,
            "description": "Đầu karaoke CAF QS-108 entry-level với kho bài cơ bản.",
            "shortDescription": "Đầu karaoke entry-level giá rẻ",
            "specifications": "{\"Kho bài\":\"30,000+ bài\"}",
            "warranty": "12 tháng",
            "imageFile": "caf_qs-108.png",
            "stockQuantity": 30,
            "featured": false
        },
        {
            "id": "QV-DK-007",
            "name": "Dàn Karaoke Gia Đình E3 Combo 1",
            "slug": "dan-karaoke-gia-dinh-e3-combo-1",
            "categorySlug": "dan-karaoke",
            "brand": "E3 Audio",
            "priceVND": 26200000,
            "description": "Combo karaoke E3 cơ bản cho gia đình với đầy đủ thiết bị cần thiết.",
            "shortDescription": "Combo karaoke E3 cơ bản cho gia đình",
            "specifications": "{\"Loa\":\"2x E3 KC12\",\"Vang\":\"E3 K8900\",\"Micro\":\"E3 M560\"}",
            "warranty": "24 tháng",
            "imageFile": "dàn_karaoke_gia_đình_e3_combo_1.png",
            "stockQuantity": 10,
            "featured": false
        },
        {
            "id": "QV-DK-008",
            "name": "Dàn Karaoke Gia Đình CAF",
            "slug": "dan-karaoke-gia-dinh-caf",
            "categorySlug": "dan-karaoke",
            "brand": "CAF",
            "priceVND": 22500000,
            "description": "Dàn karaoke CAF phổ thông cho gia đình với giá hợp lý.",
            "shortDescription": "Dàn karaoke CAF phổ thông giá hợp lý",
            "specifications": "{\"Loa\":\"2x CAF MC12\",\"Vang\":\"CAF A5\",\"Micro\":\"CAF MH-666\"}",
            "warranty": "24 tháng",
            "imageFile": "dàn_karaoke_gia_đình_caf.png",
            "stockQuantity": 12,
            "featured": false
        }
    ]
}